{
  "id": "7635d30f",
  "name": "图片题干-左右布局3选项",
  "questionType": "choice",
  "stemType": "image",
  "optionStyle": "image",
  "variant": "image_image_side_3",
  "optionCount": 3,
  "description": "左侧大题干图 + 右侧3个竖排选项 + 配音",
  "elements": [
    {
      "id": "pre_2c",
      "presetKey": "bg_area",
      "label": "背景",
      "type": "rect",
      "color": "#94a3b8",
      "x": 0,
      "y": 0,
      "w": 1624,
      "h": 1050
    },
    {
      "id": "pre_25",
      "presetKey": "stem_image",
      "label": "题干图",
      "type": "rect",
      "color": "#0ea5e9",
      "x": 185,
      "y": 266,
      "w": 915,
      "h": 555,
      "borderRadius": {
        "tl": 30,
        "tr": 30,
        "br": 30,
        "bl": 30
      }
    },
    {
      "id": "el_05aacfa",
      "presetKey": "control_widget",
      "label": "喇叭动效",
      "type": "rect",
      "color": "#14b8a6",
      "x": 1415,
      "y": 325,
      "w": 66,
      "h": 66,
      "borderRadius": {
        "tl": 0,
        "tr": 0,
        "br": 0,
        "bl": 0
      },
      "opacity": 1,
      "widgetName": "audio",
      "assetUrl": "/widget-library/audio_apng.png",
      "assetPath": "/data/widget-library/audio_apng.png",
      "widgetConfigKey": "audioPictures",
      "hidden": false
    },
    {
      "id": "el_64clh1g",
      "presetKey": "control_widget",
      "label": "喇叭动效",
      "type": "rect",
      "color": "#14b8a6",
      "x": 1415,
      "y": 511,
      "w": 66,
      "h": 66,
      "borderRadius": {
        "tl": 0,
        "tr": 0,
        "br": 0,
        "bl": 0
      },
      "opacity": 1,
      "widgetName": "audio",
      "assetUrl": "/widget-library/audio_apng.png",
      "assetPath": "/data/widget-library/audio_apng.png",
      "widgetConfigKey": "audioPictures"
    },
    {
      "id": "el_w79phq8",
      "presetKey": "control_widget",
      "label": "喇叭动效",
      "type": "rect",
      "color": "#14b8a6",
      "x": 1415,
      "y": 697,
      "w": 66,
      "h": 66,
      "borderRadius": {
        "tl": 0,
        "tr": 0,
        "br": 0,
        "bl": 0
      },
      "opacity": 1,
      "widgetName": "audio",
      "assetUrl": "/widget-library/audio_apng.png",
      "assetPath": "/data/widget-library/audio_apng.png",
      "widgetConfigKey": "audioPictures",
      "hidden": false
    },
    {
      "id": "el_jx47bse",
      "presetKey": "animation_area",
      "label": "动效区",
      "type": "rect",
      "color": "#a855f7",
      "x": 355,
      "y": 266,
      "w": 915,
      "h": 555,
      "borderRadius": {
        "tl": 30,
        "tr": 30,
        "br": 30,
        "bl": 30
      },
      "opacity": 1,
      "hidden": false,
      "locked": true
    },
    {
      "id": "el_pwp347k",
      "presetKey": "anim_cover",
      "label": "白边覆盖区",
      "type": "rect",
      "color": "#d946ef",
      "x": 112,
      "y": 266.5,
      "w": 1400,
      "h": 555,
      "borderRadius": {
        "tl": 30,
        "tr": 30,
        "br": 30,
        "bl": 30
      },
      "opacity": 1,
      "hidden": false,
      "locked": true
    },
    {
      "id": "el_bpn1wzr",
      "presetKey": "text_label",
      "label": "文字标签",
      "type": "text",
      "color": "#f59e0b",
      "x": 1170,
      "y": 328,
      "w": 200,
      "h": 60,
      "borderRadius": 20,
      "opacity": 1,
      "textContent": "示例文字",
      "fontSize": 28,
      "textColor": "#1e3a8a",
      "fontFamily": "\"PingFang SC\", sans-serif",
      "fontWeight": "bold",
      "textAlign": "center",
      "groupId": "grp_i8jt3",
      "groupName": "选项区"
    },
    {
      "id": "el_qjnq9tb",
      "presetKey": "text_label",
      "label": "文字标签",
      "type": "text",
      "color": "#f59e0b",
      "x": 1170,
      "y": 514,
      "w": 200,
      "h": 60,
      "borderRadius": 20,
      "opacity": 1,
      "textContent": "示例文字",
      "fontSize": 28,
      "textColor": "#1e3a8a",
      "fontFamily": "\"PingFang SC\", sans-serif",
      "fontWeight": "bold",
      "textAlign": "center",
      "groupId": "grp_i8jt3",
      "groupName": "选项区"
    },
    {
      "id": "el_8add68m",
      "presetKey": "text_label",
      "label": "文字标签",
      "type": "text",
      "color": "#f59e0b",
      "x": 1170,
      "y": 700,
      "w": 200,
      "h": 60,
      "borderRadius": 20,
      "opacity": 1,
      "textContent": "示例文字",
      "fontSize": 28,
      "textColor": "#1e3a8a",
      "fontFamily": "\"PingFang SC\", sans-serif",
      "fontWeight": "bold",
      "textAlign": "center",
      "groupId": "grp_i8jt3",
      "groupName": "选项区"
    }
  ],
  "isPreset": true,
  "canvasWidth": 1624,
  "canvasHeight": 1050,
  "createdAt": 1775128148231,
  "updatedAt": 1776599679366,
  "status": "completed",
  "safeTop": 150,
  "safeBottom": 900,
  "canvasPresetId": "default",
  "optionStates": {
    "normal": {
      "borderWidth": 6,
      "borderColor": "#ffffff",
      "borderOpacity": 0,
      "borderStyle": "solid",
      "lineCap": "butt",
      "dashLength": 12,
      "dashGap": 6,
      "borderGap": 24,
      "borderRadius": 30,
      "fillColor": "#ffffff",
      "fillOpacity": 0
    },
    "selected": {
      "borderWidth": 6,
      "borderColor": "#ffc933",
      "borderOpacity": 1,
      "borderStyle": "solid",
      "lineCap": "round",
      "dashLength": 12,
      "dashGap": 6,
      "borderGap": 24,
      "borderRadius": 30,
      "fillColor": "#ffc933",
      "fillOpacity": 0
    },
    "correct": {
      "borderWidth": 6,
      "borderColor": "#00cc66",
      "borderOpacity": 1,
      "borderStyle": "solid",
      "lineCap": "round",
      "dashLength": 12,
      "dashGap": 6,
      "borderGap": 24,
      "borderRadius": 30,
      "fillColor": "#00cc66",
      "fillOpacity": 0.2
    }
  },
  "textStyle": {
    "fontFamily": "方正粗圆斑马英语",
    "fontSize": 36,
    "fontColor": "#2f4d90",
    "bgColor": "#ffffff",
    "align": "center",
    "letterSpacing": 0
  },
  "animationSettings": {
    "fps": 10,
    "maxColors": 256,
    "dither": "floyd_steinberg"
  }
}